{
    "asset": {
        "format": "JPG",
        "id": "16fa57c75a2063d9d645a2d36c12f3c6",
        "name": "2018_NB04_021288.JPG",
        "path": "file:Z:/biome_health_project_files/country_files/kenya/tagging_photos/2/2018_NB04_021288.JPG",
        "size": {
            "width": 2688,
            "height": 1512
        },
        "state": 2,
        "type": 1
    },
    "regions": [
        {
            "id": "KEydDHYLQ",
            "type": "RECTANGLE",
            "tags": [
                "53_unidentified"
            ],
            "boundingBox": {
                "height": 111.02097902097903,
                "width": 149.72477064220183,
                "left": 322.34862385321105,
                "top": 507.85489510489515
            },
            "points": [
                {
                    "x": 322.34862385321105,
                    "y": 507.85489510489515
                },
                {
                    "x": 472.07339449541286,
                    "y": 507.85489510489515
                },
                {
                    "x": 472.07339449541286,
                    "y": 618.8758741258741
                },
                {
                    "x": 322.34862385321105,
                    "y": 618.8758741258741
                }
            ]
        },
        {
            "id": "RmJ0G5ZVK",
            "type": "RECTANGLE",
            "tags": [
                "53_unidentified"
            ],
            "boundingBox": {
                "height": 133.93006993006995,
                "width": 200.8073394495413,
                "left": 776.8073394495414,
                "top": 491.99475524475525
            },
            "points": [
                {
                    "x": 776.8073394495414,
                    "y": 491.99475524475525
                },
                {
                    "x": 977.6146788990826,
                    "y": 491.99475524475525
                },
                {
                    "x": 977.6146788990826,
                    "y": 625.9248251748252
                },
                {
                    "x": 776.8073394495414,
                    "y": 625.9248251748252
                }
            ]
        },
        {
            "id": "2dE4hzH9n",
            "type": "RECTANGLE",
            "tags": [
                "53_unidentified"
            ],
            "boundingBox": {
                "height": 151.55244755244755,
                "width": 213.1376146788991,
                "left": 1342.238532110092,
                "top": 509.6171328671329
            },
            "points": [
                {
                    "x": 1342.238532110092,
                    "y": 509.6171328671329
                },
                {
                    "x": 1555.3761467889908,
                    "y": 509.6171328671329
                },
                {
                    "x": 1555.3761467889908,
                    "y": 661.1695804195805
                },
                {
                    "x": 1342.238532110092,
                    "y": 661.1695804195805
                }
            ]
        },
        {
            "id": "DueqQvLMH",
            "type": "RECTANGLE",
            "tags": [
                "53_unidentified"
            ],
            "boundingBox": {
                "height": 148.02797202797203,
                "width": 241.3211009174312,
                "left": 1920,
                "top": 520.1905594405595
            },
            "points": [
                {
                    "x": 1920,
                    "y": 520.1905594405595
                },
                {
                    "x": 2161.3211009174315,
                    "y": 520.1905594405595
                },
                {
                    "x": 2161.3211009174315,
                    "y": 668.2185314685315
                },
                {
                    "x": 1920,
                    "y": 668.2185314685315
                }
            ]
        }
    ],
    "version": "2.0.0"
}