{
    "asset": {
        "format": "JPG",
        "id": "3018471fb576ca2268749415bcc48d95",
        "name": "2018_NB20_003874.JPG",
        "path": "file:Z:/biome_health_project_files/country_files/kenya/tagging_photos/1/2018_NB20_003874.JPG",
        "size": {
            "width": 2688,
            "height": 1512
        },
        "state": 2,
        "type": 1
    },
    "regions": [
        {
            "id": "nB9naZ56h",
            "type": "RECTANGLE",
            "tags": [
                "46_wildebeest"
            ],
            "boundingBox": {
                "height": 452.4963503649635,
                "width": 537.2320328542095,
                "left": 379.006160164271,
                "top": 696.9662408759124
            },
            "points": [
                {
                    "x": 379.006160164271,
                    "y": 696.9662408759124
                },
                {
                    "x": 916.2381930184805,
                    "y": 696.9662408759124
                },
                {
                    "x": 916.2381930184805,
                    "y": 1149.462591240876
                },
                {
                    "x": 379.006160164271,
                    "y": 1149.462591240876
                }
            ]
        }
    ],
    "version": "2.0.0"
}