{
    "asset": {
        "format": "JPG",
        "id": "6796be71a24409d35110e31d0f20acdf",
        "name": "2018_MN16_003402.JPG",
        "path": "file:Z:/biome_health_project_files/country_files/kenya/tagging_photos/1/2018_MN16_003402.JPG",
        "size": {
            "width": 2688,
            "height": 1512
        },
        "state": 2,
        "type": 1
    },
    "regions": [
        {
            "id": "DwNZJFn8X",
            "type": "RECTANGLE",
            "tags": [
                "47_zebra"
            ],
            "boundingBox": {
                "height": 665.2058823529412,
                "width": 746.5637491385252,
                "left": 1928.4686423156443,
                "top": 248.46783088235296
            },
            "points": [
                {
                    "x": 1928.4686423156443,
                    "y": 248.46783088235296
                },
                {
                    "x": 2675.0323914541696,
                    "y": 248.46783088235296
                },
                {
                    "x": 2675.0323914541696,
                    "y": 913.6737132352941
                },
                {
                    "x": 1928.4686423156443,
                    "y": 913.6737132352941
                }
            ]
        }
    ],
    "version": "2.0.0"
}