{
    "asset": {
        "format": "JPG",
        "id": "870558bb4e325eefa66a8b7e81bb28a3",
        "name": "2018_MT42_005422.JPG",
        "path": "file:Z:/biome_health_project_files/country_files/kenya/tagging_photos/2/2018_MT42_005422.JPG",
        "size": {
            "width": 2688,
            "height": 1512
        },
        "state": 2,
        "type": 1
    },
    "regions": [
        {
            "id": "n8Jt8AEqw",
            "type": "RECTANGLE",
            "tags": [
                "4_buffalo"
            ],
            "boundingBox": {
                "height": 139.21678321678323,
                "width": 188.4770642201835,
                "left": 1574.7522935779818,
                "top": 715.798951048951
            },
            "points": [
                {
                    "x": 1574.7522935779818,
                    "y": 715.798951048951
                },
                {
                    "x": 1763.2293577981652,
                    "y": 715.798951048951
                },
                {
                    "x": 1763.2293577981652,
                    "y": 855.0157342657343
                },
                {
                    "x": 1574.7522935779818,
                    "y": 855.0157342657343
                }
            ]
        },
        {
            "id": "C8m7oXzSZ",
            "type": "RECTANGLE",
            "tags": [
                "4_buffalo"
            ],
            "boundingBox": {
                "height": 123.35664335664336,
                "width": 156.77064220183487,
                "left": 1472.5871559633028,
                "top": 733.4213286713288
            },
            "points": [
                {
                    "x": 1472.5871559633028,
                    "y": 733.4213286713288
                },
                {
                    "x": 1629.3577981651376,
                    "y": 733.4213286713288
                },
                {
                    "x": 1629.3577981651376,
                    "y": 856.777972027972
                },
                {
                    "x": 1472.5871559633028,
                    "y": 856.777972027972
                }
            ]
        },
        {
            "id": "S5QyVDf4_",
            "type": "RECTANGLE",
            "tags": [
                "4_buffalo"
            ],
            "boundingBox": {
                "height": 162.12587412587413,
                "width": 264.22018348623857,
                "left": 2418.4954128440368,
                "top": 738.708041958042
            },
            "points": [
                {
                    "x": 2418.4954128440368,
                    "y": 738.708041958042
                },
                {
                    "x": 2682.7155963302753,
                    "y": 738.708041958042
                },
                {
                    "x": 2682.7155963302753,
                    "y": 900.8339160839162
                },
                {
                    "x": 2418.4954128440368,
                    "y": 900.8339160839162
                }
            ]
        },
        {
            "id": "r3bKuzIMn",
            "type": "RECTANGLE",
            "tags": [
                "4_buffalo"
            ],
            "boundingBox": {
                "height": 153.3146853146853,
                "width": 95.11926605504587,
                "left": 2348.0366972477063,
                "top": 742.2325174825176
            },
            "points": [
                {
                    "x": 2348.0366972477063,
                    "y": 742.2325174825176
                },
                {
                    "x": 2443.1559633027523,
                    "y": 742.2325174825176
                },
                {
                    "x": 2443.1559633027523,
                    "y": 895.5472027972028
                },
                {
                    "x": 2348.0366972477063,
                    "y": 895.5472027972028
                }
            ]
        }
    ],
    "version": "2.0.0"
}