{
    "asset": {
        "format": "JPG",
        "id": "a5155585b2d6845ddbe6adca4e96781b",
        "name": "2018_MT02_000068.JPG",
        "path": "file:Z:/biome_health_project_files/country_files/kenya/tagging_photos/2/2018_MT02_000068.JPG",
        "size": {
            "width": 2688,
            "height": 1512
        },
        "state": 2,
        "type": 1
    },
    "regions": [
        {
            "id": "7r-LxbnYY",
            "type": "RECTANGLE",
            "tags": [
                "21_human"
            ],
            "boundingBox": {
                "height": 927.5368421052631,
                "width": 217.5157894736842,
                "left": 2470.4842105263156,
                "top": 0
            },
            "points": [
                {
                    "x": 2470.4842105263156,
                    "y": 0
                },
                {
                    "x": 2688,
                    "y": 0
                },
                {
                    "x": 2688,
                    "y": 927.5368421052631
                },
                {
                    "x": 2470.4842105263156,
                    "y": 927.5368421052631
                }
            ]
        }
    ],
    "version": "2.0.0"
}