{
    "asset": {
        "format": "JPG",
        "id": "c58f91f5639f9ff0d68063587b9d08c6",
        "name": "2018_NB11_002578.JPG",
        "path": "file:Z:/biome_health_project_files/country_files/kenya/tagging_photos/2/2018_NB11_002578.JPG",
        "size": {
            "width": 2688,
            "height": 1512
        },
        "state": 2,
        "type": 1
    },
    "regions": [
        {
            "id": "UtFb-NGQs",
            "type": "RECTANGLE",
            "tags": [
                "11_elephant"
            ],
            "boundingBox": {
                "height": 429.986013986014,
                "width": 621.7981651376147,
                "left": 1768.51376146789,
                "top": 514.9038461538462
            },
            "points": [
                {
                    "x": 1768.51376146789,
                    "y": 514.9038461538462
                },
                {
                    "x": 2390.3119266055046,
                    "y": 514.9038461538462
                },
                {
                    "x": 2390.3119266055046,
                    "y": 944.8898601398602
                },
                {
                    "x": 1768.51376146789,
                    "y": 944.8898601398602
                }
            ]
        },
        {
            "id": "PtLJd-VSv",
            "type": "RECTANGLE",
            "tags": [
                "11_elephant"
            ],
            "boundingBox": {
                "height": 1457.701048951049,
                "width": 618.2752293577983,
                "left": 0,
                "top": 0
            },
            "points": [
                {
                    "x": 0,
                    "y": 0
                },
                {
                    "x": 618.2752293577983,
                    "y": 0
                },
                {
                    "x": 618.2752293577983,
                    "y": 1457.701048951049
                },
                {
                    "x": 0,
                    "y": 1457.701048951049
                }
            ]
        }
    ],
    "version": "2.0.0"
}