{
    "asset": {
        "format": "JPG",
        "id": "d2c9ac8ef59a65bce72d55c7f86401d4",
        "name": "2018_NB26_009283.JPG",
        "path": "file:Z:/biome_health_project_files/country_files/kenya/tagging_photos/1/2018_NB26_009283.JPG",
        "size": {
            "width": 2688,
            "height": 1512
        },
        "state": 2,
        "type": 1
    },
    "regions": [
        {
            "id": "fpOGBZ0bA",
            "type": "RECTANGLE",
            "tags": [
                "46_wildebeest"
            ],
            "boundingBox": {
                "height": 57.93819530284301,
                "width": 54.17095205003475,
                "left": 2226.6129256428076,
                "top": 760.1467861557478
            },
            "points": [
                {
                    "x": 2226.6129256428076,
                    "y": 760.1467861557478
                },
                {
                    "x": 2280.7838776928425,
                    "y": 760.1467861557478
                },
                {
                    "x": 2280.7838776928425,
                    "y": 818.0849814585908
                },
                {
                    "x": 2226.6129256428076,
                    "y": 818.0849814585908
                }
            ]
        },
        {
            "id": "NFFK_xYB1",
            "type": "RECTANGLE",
            "tags": [
                "46_wildebeest"
            ],
            "boundingBox": {
                "height": 56.06922126081582,
                "width": 56.03891591382905,
                "left": 2032.3446838082002,
                "top": 747.0639678615574
            },
            "points": [
                {
                    "x": 2032.3446838082002,
                    "y": 747.0639678615574
                },
                {
                    "x": 2088.3835997220294,
                    "y": 747.0639678615574
                },
                {
                    "x": 2088.3835997220294,
                    "y": 803.1331891223733
                },
                {
                    "x": 2032.3446838082002,
                    "y": 803.1331891223733
                }
            ]
        },
        {
            "id": "ue7n_fy6e",
            "type": "RECTANGLE",
            "tags": [
                "46_wildebeest"
            ],
            "boundingBox": {
                "height": 65.41409147095179,
                "width": 50.43502432244615,
                "left": 341.8373870743572,
                "top": 605.0219406674908
            },
            "points": [
                {
                    "x": 341.8373870743572,
                    "y": 605.0219406674908
                },
                {
                    "x": 392.27241139680336,
                    "y": 605.0219406674908
                },
                {
                    "x": 392.27241139680336,
                    "y": 670.4360321384426
                },
                {
                    "x": 341.8373870743572,
                    "y": 670.4360321384426
                }
            ]
        },
        {
            "id": "nVOnpEi8M",
            "type": "RECTANGLE",
            "tags": [
                "46_wildebeest"
            ],
            "boundingBox": {
                "height": 35.51050679851669,
                "width": 78.45448227936068,
                "left": 267.11883252258514,
                "top": 633.0565512978986
            },
            "points": [
                {
                    "x": 267.11883252258514,
                    "y": 633.0565512978986
                },
                {
                    "x": 345.5733148019458,
                    "y": 633.0565512978986
                },
                {
                    "x": 345.5733148019458,
                    "y": 668.5670580964153
                },
                {
                    "x": 267.11883252258514,
                    "y": 668.5670580964153
                }
            ]
        },
        {
            "id": "nQXC1S2Fo",
            "type": "RECTANGLE",
            "tags": [
                "12_gazelle_grants"
            ],
            "boundingBox": {
                "height": 663.485784919654,
                "width": 588.408617095205,
                "left": 297.00625434329396,
                "top": 334.0207045735476
            },
            "points": [
                {
                    "x": 297.00625434329396,
                    "y": 334.0207045735476
                },
                {
                    "x": 885.414871438499,
                    "y": 334.0207045735476
                },
                {
                    "x": 885.414871438499,
                    "y": 997.5064894932015
                },
                {
                    "x": 297.00625434329396,
                    "y": 997.5064894932015
                }
            ]
        }
    ],
    "version": "2.0.0"
}