{
    "asset": {
        "format": "JPG",
        "id": "de86130dea12ab55dd3b7e0268ea04a4",
        "name": "2018_MT34_020265.JPG",
        "path": "file:Z:/biome_health_project_files/country_files/kenya/tagging_photos/1/2018_MT34_020265.JPG",
        "size": {
            "width": 2688,
            "height": 1512
        },
        "state": 2,
        "type": 1
    },
    "regions": [
        {
            "id": "LmApq61hd",
            "type": "RECTANGLE",
            "tags": [
                "47_zebra"
            ],
            "boundingBox": {
                "height": 334.6082840236686,
                "width": 647.4091816367265,
                "left": 906.7305389221557,
                "top": 448.6233727810651
            },
            "points": [
                {
                    "x": 906.7305389221557,
                    "y": 448.6233727810651
                },
                {
                    "x": 1554.1397205588821,
                    "y": 448.6233727810651
                },
                {
                    "x": 1554.1397205588821,
                    "y": 783.2316568047337
                },
                {
                    "x": 906.7305389221557,
                    "y": 783.2316568047337
                }
            ]
        },
        {
            "id": "skNKu5N8a",
            "type": "RECTANGLE",
            "tags": [
                "47_zebra"
            ],
            "boundingBox": {
                "height": 465.2307692307692,
                "width": 836.9820359281437,
                "left": 1087.3612774451099,
                "top": 362.7346153846154
            },
            "points": [
                {
                    "x": 1087.3612774451099,
                    "y": 362.7346153846154
                },
                {
                    "x": 1924.3433133732535,
                    "y": 362.7346153846154
                },
                {
                    "x": 1924.3433133732535,
                    "y": 827.9653846153846
                },
                {
                    "x": 1087.3612774451099,
                    "y": 827.9653846153846
                }
            ]
        }
    ],
    "version": "2.0.0"
}